{
  "id": "36-2021",
  "title": "Nick\u2019s Famous Bar-B-Q Recalls Ready-To-Eat Pork Products  Due to Possible Listeria Contamination",
  "url": "https://www.fsis.usda.gov/recalls-alerts/nicks-famous-bar-b-q-recalls-ready-eat-pork-products-due-possible-listeria",
  "reasons": [
    "Product Contamination"
  ],
  "status": "Closed",
  "risk_level": "High",
  "start_date": "2021-10-08",
  "end_date": "2021-10-22",
  "summary": "WASHINGTON, Oct. 8, 2021 \u2013 Nick\u2019s Famous Bar-B-Q, a Nashville, Tenn., establishment, is recalling approximately 3,140 pounds of ready-to-eat (RTE) smoked pork barbecue products that may be adulterated with Listeria monocytogenes, the U.S. Department of Agriculture\u2019s Food Safety and Inspection Service (FSIS) announced today. The...",
  "establishment": {
    "id": "M17863+P17863",
    "url": "http://www.fsis.usda.gov/inspection/fsis-inspected-establishments/i-65-bbq-inc",
    "slug": "i-65-bbq-inc",
    "name": "I-65 BBQ, Inc.",
    "address": "2817  Clarksville Pk. \n  Nashville, TN 37208",
    "telephone": "(615) 248-6365",
    "grant_date": "2020-03-17",
    "activities": [
      "Meat Processing",
      "Poultry Processing"
    ]
  },
  "impacted_products": [
    "20-lb. boxes of \u201cNick\u2019s FAMOUS Hickory Smoked Pork Bar-B-Q\u201d with a case code of 23452 and a use by date of 09/2022."
  ],
  "quantity_recovered": null,
  "quantity_unit": null,
  "states": [
    "North Carolina"
  ]
}