{
  "id": "PHA-092812-01",
  "title": "FSIS Expands Public Health Alert for Imported Canadian Beef from XL Foods-092812",
  "url": "https://www.fsis.usda.gov/recalls-alerts/fsis-expands-public-health-alert-imported-canadian-beef-xl-foods-092812",
  "reasons": [
    "Product Contamination"
  ],
  "status": "Active",
  "risk_level": null,
  "start_date": "2012-09-28",
  "end_date": null,
  "summary": "Editors Note: The third paragraph of this Public Health Alert was updated on October 5, 2012 to reflect the approximate amount of products imported into the U.S. by XL Foods, Inc. WASHINGTON, September 28, 2012 - The USDA's Food Safety and Inspection Service (FSIS) is...",
  "establishment": null,
  "impacted_products": [],
  "quantity_recovered": null,
  "quantity_unit": null,
  "states": null
}