{"id": "055-2012", "title": "Utah Firm Recalls Beef Products Due To Possible E. Coli O157:H7 Contamination", "url": "https://www.fsis.usda.gov/recalls-alerts/utah-firm-recalls-beef-products-due-possible-e.-coli-o157h7-contamination", "reasons": ["Product Contamination"], "status": "Closed", "risk_level": "High", "start_date": "2012-08-14", "end_date": null, "summary": "WASHINGTON, August 14, 2012 - Dale T. Smith and Sons Meat Packing, a Draper, Utah establishment, is recalling approximately 38,200 pounds of beef products that may be contaminated with E. coli O157:H7, the U.S. Department of Agriculture's Food Safety and Inspection Service (FSIS) announced today...\n", "establishment": {"id": "M4975+P4975", "url": "http://www.fsis.usda.gov/inspection/fsis-inspected-establishments/dale-t.-smith-and-sons-meat-packing-company-inc", "slug": "dale-t-smith-and-sons-meat-packing-company-inc", "name": "Dale T. Smith and Sons Meat Packing Company Inc", "address": "12450 South Pony Express Road \n  Draper, UT 84020", "telephone": "(801) 571-3611", "grant_date": "2016-05-05", "activities": ["Meat Processing", "Meat Slaughter", "Poultry Processing"]}, "impacted_products": ["Various weight combo bins of Boneless Beef \"50/50,\" \"85/15,\" \"90/10,\" \"93/07\" or \"95/05\" produced on Aug. 7, 2012."], "quantity_recovered": 327700, "quantity_unit": "pounds", "states": null}
