{
  "id": "070-2012",
  "title": "Texas Firm Recalls Chicken Enchilada Products That May Contain Foreign Materials",
  "url": "https://www.fsis.usda.gov/recalls-alerts/texas-firm-recalls-chicken-enchilada-products-may-contain-foreign-materials",
  "reasons": [
    "Product Contamination"
  ],
  "status": "Closed",
  "risk_level": "Low",
  "start_date": "2012-10-30",
  "end_date": "2013-06-01",
  "summary": "WASHINGTON, Oct. 30, 2012 - Food Source, L.P., a McKinney, Texas, establishment, is recalling approximately 11,400 pounds of frozen chicken enchilada products that may contain foreign materials, fragments of plastic, the U.S. Department of Agriculture's Food Safety and Inspection Service (FSIS) announced today. The products...\n",
  "establishment": {
    "id": "M13130+P13130",
    "url": "http://www.fsis.usda.gov/inspection/fsis-inspected-establishments/blount-fine-foods-corp",
    "slug": "blount-fine-foods-corp",
    "name": "Blount Fine Foods Corp.",
    "address": "2200 Redbud Boulevard \n  McKinney, TX 75069",
    "telephone": "(972) 548-9001",
    "grant_date": "2016-01-21",
    "activities": [
      "Meat Processing",
      "Poultry Processing"
    ]
  },
  "impacted_products": [
    "57-oz. boxes of \"Bremer Party Size White Meat Chicken Enchiladas\""
  ],
  "quantity_recovered": 27623,
  "quantity_unit": "pounds",
  "states": [
    "New York",
    "Ohio",
    "Pennsylvania",
    "West Virginia"
  ]
}