{
  "id": "081-2018",
  "title": "Cargill Meat Solutions Recalls Ground Beef Products due to Possible E. coli O26 Contamination",
  "url": "https://www.fsis.usda.gov/recalls-alerts/cargill-meat-solutions-recalls-ground-beef-products-due-possible-e.-coli-o26",
  "reasons": [
    "Product Contamination"
  ],
  "status": "Closed",
  "risk_level": "High",
  "start_date": "2018-09-19",
  "end_date": "2019-04-26",
  "summary": "WASHINGTON, Sept. 19, 2018 Cargill Meat Solutions, a Fort Morgan, Colo. establishment, is recalling approximately 132,606 pounds of ground beef products made from the chuck portion of the carcass that may be contaminated with Escherichia coli O26, the U.S. Department of Agricultures Food Safety and...",
  "establishment": {
    "id": "M86R",
    "url": "http://www.fsis.usda.gov/inspection/fsis-inspected-establishments/cargill-meat-solutions-8",
    "slug": "cargill-meat-solutions-8",
    "name": "Cargill Meat Solutions",
    "address": "1505 East Burlington Avenue \n  Fort Morgan, CO 80701",
    "telephone": "(970) 867-8223",
    "grant_date": "2019-03-22",
    "activities": [
      "Meat Processing",
      "Meat Slaughter"
    ]
  },
  "impacted_products": [],
  "quantity_recovered": 0,
  "quantity_unit": "pounds",
  "states": null
}