{"id": "026-2011", "title": "California Firm Recalls Pizza Products Due to Mislabeling and Undeclared Allergen", "url": "https://www.fsis.usda.gov/recalls-alerts/california-firm-recalls-pizza-products-due-mislabeling-and-undeclared-allergen", "reasons": ["Unreported Allergens", "Mislabeling"], "status": "Closed", "risk_level": "Low", "start_date": "2011-03-29", "end_date": null, "summary": "WASHINGTON, March 29, 2011 -Completely Fresh Foods Inc., a Montebello, Calif., establishment is voluntarily recalling approximately 131,000 pounds of pizza products because they contain an allergen, wheat, not declared on the label. Wheat is a known allergen. The products subject to recall include: 10-oz. packages...\n", "establishment": null, "impacted_products": ["10-oz. packages of \"TRADER JOE'S PIZZA AL POLLO ASADO.\" (Frozen)"], "quantity_recovered": 101216, "quantity_unit": "pounds", "states": null}
